multifutures/__init__.py
multifutures/_common.py
multifutures/_multi.py
multifutures/_rate_limit.py
multifutures/py.typed
multifutures-0.3.2.dist-info/LICENSE.txt
multifutures-0.3.2.dist-info/METADATA
multifutures-0.3.2.dist-info/WHEEL
multifutures-0.3.2.dist-info/RECORD
