Metadata-Version: 2.1
Name: multifutures
Version: 0.3.2
Summary: Multiprocessing/multithreading made easy
Author: Panos Mavrogiorgos
Author-email: pmav99@gmail.com
Requires-Python: >=3.9
Classifier: Programming Language :: Python :: 3
Classifier: Programming Language :: Python :: 3.9
Classifier: Programming Language :: Python :: 3.10
Classifier: Programming Language :: Python :: 3.11
Classifier: Programming Language :: Python :: 3.12
Provides-Extra: full
Requires-Dist: exceptiongroup
Requires-Dist: limits
Requires-Dist: loky ; extra == "full"
Requires-Dist: psutil ; extra == "full"
Requires-Dist: tqdm
